README.md
setup.cfg
setup.py
yuui/__init__.py
yuui.egg-info/PKG-INFO
yuui.egg-info/SOURCES.txt
yuui.egg-info/dependency_links.txt
yuui.egg-info/top_level.txt