Metadata-Version: 2.1
Name: yuui
Version: 2024.7.17
Summary: A program based on pygame.You can use it made GUI program easily.
Author: yuzijiang
Author-email: Toy142hjkl@hotmail.com
Keywords: python,menu,yuui,pygame,gui,yuzijiang,windows,macos,linux
Classifier: Development Status :: 1 - Planning
Classifier: Intended Audience :: Developers
Classifier: Programming Language :: Python :: 3
Classifier: Operating System :: Unix
Classifier: Operating System :: MacOS :: MacOS X
Classifier: Operating System :: Microsoft :: Windows
